tclidemo1/__init__.py
tclidemo1/main.py
tclidemo1-0.1.2.dist-info/entry_points.txt
tclidemo1-0.1.2.dist-info/WHEEL
tclidemo1-0.1.2.dist-info/METADATA
tclidemo1-0.1.2.dist-info/RECORD
