Metadata-Version: 2.1
Name: tclidemo1
Version: 0.1.2
Summary: 
Author: zy7y
Author-email: xxxx@163.com
Requires-Python: >=3.9,<4.0
Classifier: Programming Language :: Python :: 3
Classifier: Programming Language :: Python :: 3.9
Requires-Dist: typer (>=0.4.0,<0.5.0)
